{
  "projects": [
    {
      "name": "Desenvolvedor Fortan",
      "budget": "15000",
      "category": {
        "id": "3",
        "name": "Design"
      },
      "cost": 3000,
      "services": [
        {
          "name": "Layout Web com Fortan",
          "cost": "3000",
          "description": "É realmente possível?",
          "id": "aa8d1367-3f2e-4eeb-a6e0-b7c1af58cb29"
        }
      ],
      "id": 1
    },
    {
      "name": "Desenvolvedor COBOL",
      "budget": "4500",
      "category": {
        "id": "2",
        "name": "Desenvolvimento"
      },
      "cost": 4000,
      "services": [
        {
          "name": "Backend",
          "cost": "4000",
          "description": "Vai demorar, mas funciona...",
          "id": "cb03d5d4-3c60-4cce-b55b-7eb0d4cc88e8"
        }
      ],
      "id": 2
    },
    {
      "name": "Desenvolvedor Assembly",
      "budget": "5000",
      "category": {
        "id": "1",
        "name": "Infra"
      },
      "cost": 652,
      "services": [
        {
          "name": "N teste",
          "cost": "652",
          "description": "polims",
          "id": "34b9d2ad-3ed6-45d5-8637-2d8ed9727326"
        }
      ],
      "id": 3
    }
  ],
  "categories": [
    {
      "id": 1,
      "name": "Infra"
    },
    {
      "id": 2,
      "name": "Desenvolvimento"
    },
    {
      "id": 3,
      "name": "Design"
    },
    {
      "id": 4,
      "name": "Planejamento"
    }
  ]
}